qikpropservice/__init__.py
qikpropservice/_version.py
qikpropservice/data_models.py
qikpropservice/hashing.py
qikpropservice/qpcli.py
qikpropservice/qplib.py
qikpropservice-0.2.4.dist-info/LICENSE
qikpropservice-0.2.4.dist-info/METADATA
qikpropservice-0.2.4.dist-info/WHEEL
qikpropservice-0.2.4.dist-info/entry_points.txt
qikpropservice-0.2.4.dist-info/top_level.txt
qikpropservice-0.2.4.dist-info/zip-safe
qikpropservice-0.2.4.dist-info/RECORD
