Metadata-Version: 2.1
Name: qikpropservice
Version: 0.2.4
Summary: API wrapper CLI and library for MolSSI QikProp as a Service
Home-page: https://github.com/MolSSI/qikpropservice
Author: Levi Naden
Author-email: lnaden@vt.edu
License: MIT
Platform: UNKNOWN
Classifier: Development Status :: 4 - Beta
Classifier: Intended Audience :: Science/Research
Classifier: Programming Language :: Python :: 3
Requires-Dist: requests
Requires-Dist: click
Requires-Dist: pydantic
Requires-Dist: tqdm
Provides-Extra: tests
Requires-Dist: pytest ; extra == 'tests'
Requires-Dist: pytest-cov ; extra == 'tests'
